oneforall_kjl/__init__.py
oneforall_kjl/brute.py
oneforall_kjl/export.py
oneforall_kjl/oneforall.py
oneforall_kjl/takeover.py
oneforall_kjl/test.py
oneforall_kjl/common/__init__.py
oneforall_kjl/common/check.py
oneforall_kjl/common/crawl.py
oneforall_kjl/common/database.py
oneforall_kjl/common/domain.py
oneforall_kjl/common/ipasn.py
oneforall_kjl/common/ipreg.py
oneforall_kjl/common/lookup.py
oneforall_kjl/common/module.py
oneforall_kjl/common/query.py
oneforall_kjl/common/records.py
oneforall_kjl/common/request.py
oneforall_kjl/common/resolve.py
oneforall_kjl/common/search.py
oneforall_kjl/common/similarity.py
oneforall_kjl/common/tldextract.py
oneforall_kjl/common/utils.py
oneforall_kjl/common/tablib/__init__.py
oneforall_kjl/common/tablib/format.py
oneforall_kjl/common/tablib/tablib.py
oneforall_kjl/config/__init__.py
oneforall_kjl/config/api.py
oneforall_kjl/config/default.py
oneforall_kjl/config/log.py
oneforall_kjl/config/setting.py
oneforall_kjl/data/altdns_wordlist.txt
oneforall_kjl/data/authoritative_dns.txt
oneforall_kjl/data/cdn_asn_list.json
oneforall_kjl/data/cdn_cname_keywords.json
oneforall_kjl/data/cdn_header_keys.json
oneforall_kjl/data/cdn_ip_cidr.json
oneforall_kjl/data/common_js_library.json
oneforall_kjl/data/fingerprints.json
oneforall_kjl/data/ip2location.zip
oneforall_kjl/data/ip2region.db
oneforall_kjl/data/nameservers.txt
oneforall_kjl/data/nameservers_cn.txt
oneforall_kjl/data/public_suffix_list.dat
oneforall_kjl/data/srv_prefixes.json
oneforall_kjl/data/subnames.txt
oneforall_kjl/data/subnames_big.7z
oneforall_kjl/data/subnames_medium.txt
oneforall_kjl/data/subnames_next.txt
oneforall_kjl/modules/__init__.py
oneforall_kjl/modules/altdns.py
oneforall_kjl/modules/collect.py
oneforall_kjl/modules/enrich.py
oneforall_kjl/modules/finder.py
oneforall_kjl/modules/iscdn.py
oneforall_kjl/modules/srv.py
oneforall_kjl/modules/wildcard.py
oneforall_kjl/modules/autotake/github.py
oneforall_kjl/modules/certificates/censys_api.py
oneforall_kjl-0.1.20.dist-info/METADATA
oneforall_kjl-0.1.20.dist-info/WHEEL
oneforall_kjl-0.1.20.dist-info/entry_points.txt
oneforall_kjl-0.1.20.dist-info/top_level.txt
oneforall_kjl-0.1.20.dist-info/RECORD
